nextwave/__init__.py
nextwave/abc.py
nextwave/backoff.py
nextwave/enums.py
nextwave/errors.py
nextwave/filters.py
nextwave/player.py
nextwave/pool.py
nextwave/queue.py
nextwave/stats.py
nextwave/tracks.py
nextwave/utils.py
nextwave/websocket.py
nextwave/ext/spotify/__init__.py
nextwave/types/__init__.py
nextwave/types/queue.py
nextwave-1.5.dist-info/LICENSE
nextwave-1.5.dist-info/METADATA
nextwave-1.5.dist-info/WHEEL
nextwave-1.5.dist-info/nextwave-1.1.tar.gz
nextwave-1.5.dist-info/top_level.txt
nextwave-1.5.dist-info/RECORD
