Metadata-Version: 2.1
Name: nextwave
Version: 1.5
Summary: A  robust and powerful Lavalink wrapper for nextcord and derivatives.
Home-page: https://github.com/abindent/nextwave/
Author: PythonistaGuild, EvieePy, Sinchan Maitra
Author-email: smsinchanmaitra2007@gmail.com
License: MIT
Project-URL: Documentation, https://docs.nextwave.epizy.com/
Project-URL: Website, https://nextwave.epizy.com/
Classifier: License :: OSI Approved :: MIT License
Classifier: Intended Audience :: Developers
Classifier: Natural Language :: English
Classifier: Operating System :: OS Independent
Classifier: Programming Language :: Python :: 3.8
Classifier: Programming Language :: Python :: 3.9
Classifier: Programming Language :: Python :: 3.10
Classifier: Topic :: Internet
Classifier: Topic :: Software Development :: Libraries
Classifier: Topic :: Software Development :: Libraries :: Python Modules
Classifier: Topic :: Utilities
License-File: LICENSE
Requires-Dist: aiohttp (<4,>=3.6.0)
